{
  "displayName": "Коллекция заметок",
  "description": "Расширение VSCode для управления и сбора файлов заметок с тегами. Используйте чистый и интуитивно понятный интерфейс для эффективной организации заметок.",
  "noteCollection.title": "Коллекция заметок",
  "noteCollection.list.title": "Коллекция заметок",
  "noteCollection.editList.title": "Редактировать список заметок",
  "noteCollection.toggleCollapse.title": "Свернуть/развернуть все вкладки",
  "noteCollection.search.title": "Поиск заметок",
  "noteCollection.refresh.title": "Обновить",
  "noteCollection.more.title": "Дополнительные действия...",
  "noteCollection.openFile.title": "Открыть файл",
  "noteCollection.openInNewWindow.title": "Открыть в новом окне",
  "noteCollection.revealInExplorer.title": "Показать в проводнике",
  "noteCollection.deleteItem.title": "Удалить заметку",
  "noteCollection.disableItem.title": "Включить/Отключить",
  "noteCollection.editTags.title": "Редактировать теги...",
  "noteCollection.renameItem.title": "Переименовать заметку...",
  "noteCollection.exportTxt.title": "Экспорт в TXT...",
  "noteCollection.backup.title": "Экспорт файла резервной копии JSON...",
  "noteCollection.importBackup.title": "Импорт файла резервной копии JSON...",
  "noteCollection.addTag.title": "Добавить тег...",
  "noteCollection.deleteTag.title": "Удалить тег...",
  "noteCollection.importFiles.title": "Импорт файлов/папок",
  "noteCollection.renameTag.title": "Переименовать тег...",
  "noteCollection.deleteTagWithChildren": "Удалить тег",
  "noteCollection.toggleCollapseTag.title": "Развернуть/свернуть тег",
  "noteCollection.importFromText.title": "Импорт из текста...",
  "noteCollection.deleteItems.title": "Удалить выбранные заметки"
}